.gitignore
LICENSE
MANIFEST.in
README.md
requirements.txt
setup.py
src/Fattoush.egg-info/PKG-INFO
src/Fattoush.egg-info/SOURCES.txt
src/Fattoush.egg-info/dependency_links.txt
src/Fattoush.egg-info/entry_points.txt
src/Fattoush.egg-info/requires.txt
src/Fattoush.egg-info/top_level.txt
src/fattoush/README.md
src/fattoush/__init__.py
src/fattoush/namespace.py
src/fattoush/util.py
src/fattoush/config/__init__.py
src/fattoush/config/config.py
src/fattoush/config/config_group.py
src/fattoush/config/deprecated.py
src/fattoush/config/example_config.json
src/fattoush/config/version.py
src/fattoush/decorators/__init__.py
src/fattoush/decorators/step.py
src/fattoush/driver/__init__.py
src/fattoush/driver/driver.py
src/fattoush/driver/sauce.py
src/fattoush/hooks/__init__.py
src/fattoush/hooks/feature.py
src/fattoush/hooks/scenario.py
src/fattoush/hooks/step.py
src/fattoush/runner/__init__.py
src/fattoush/runner/bin.py
src/fattoush/runner/parsing.py
test/chrome_local.json
test/chrome_sauce_mac.json
test/features/browser_config.feature
test/features/browser_config.py
test/features/google.feature
test/features/google.py
test/features/terrain.py