Metadata-Version: 2.1
Name: Fattoush
Version: 0.4.0
Summary: A delicious testing framework
Home-page: https://github.com/alistair-broomhead/fattoush
Author: Alistair Broomhead
Author-email: alistair.broomhead+python@gmail.com
License: MIT
Platform: UNKNOWN
Provides-Extra: fast
